{"version": "https://jsonfeed.org/version/1.1", "title": "Help field calculator", "home_page_url": "https://hfcqgis.opendatasicilia.it/", "feed_url": "https://hfcqgis.opendatasicilia.it/feed_json_updated.json", "description": "Help funzioni calcolatore di campi di QGIS", "icon": "https://raw.githubusercontent.com/opendatasicilia/HfcQGIS-md/main/docs/img/hfc_rss.png", "authors": [{"name": "by OpenDataSicilia.it"}], "language": "it", "items": [{"id": "https://hfcqgis.opendatasicilia.it/blog/category/espressioni/page/2/", "url": "https://hfcqgis.opendatasicilia.it/blog/category/espressioni/page/2/", "title": "espressioni", "content_html": "<h1>espressioni</h1>", "image": null, "date_modified": "2025-12-30T11:22:39.967766+00:00", "date_published": "2025-12-30T11:22:39.967763+00:00", "authors": [], "tags": null}, {"id": "https://hfcqgis.opendatasicilia.it/blog/page/2/", "url": "https://hfcqgis.opendatasicilia.it/blog/page/2/", "title": "Blog", "content_html": "<h1>Blog</h1>", "image": null, "date_modified": "2025-12-30T11:22:39.964541+00:00", "date_published": "2025-12-30T11:22:39.964537+00:00", "authors": [], "tags": null}, {"id": "https://hfcqgis.opendatasicilia.it/blog/category/news/", "url": "https://hfcqgis.opendatasicilia.it/blog/category/news/", "title": "News", "content_html": "<h1>News</h1>", "image": null, "date_modified": "2025-12-30T11:22:39.961205+00:00", "date_published": "2025-12-30T11:22:39.961201+00:00", "authors": [], "tags": null}, {"id": "https://hfcqgis.opendatasicilia.it/blog/category/misure/", "url": "https://hfcqgis.opendatasicilia.it/blog/category/misure/", "title": "misure", "content_html": "<h1>misure</h1>", "image": null, "date_modified": "2025-12-30T11:22:39.957978+00:00", "date_published": "2025-12-30T11:22:39.957973+00:00", "authors": [], "tags": null}, {"id": "https://hfcqgis.opendatasicilia.it/blog/category/progetto/", "url": "https://hfcqgis.opendatasicilia.it/blog/category/progetto/", "title": "progetto", "content_html": "<h1>progetto</h1>", "image": null, "date_modified": "2025-12-30T11:22:39.954776+00:00", "date_published": "2025-12-30T11:22:39.954772+00:00", "authors": [], "tags": null}, {"id": "https://hfcqgis.opendatasicilia.it/blog/category/array/", "url": "https://hfcqgis.opendatasicilia.it/blog/category/array/", "title": "array", "content_html": "<h1>array</h1>", "image": null, "date_modified": "2025-12-30T11:22:39.951514+00:00", "date_published": "2025-12-30T11:22:39.951510+00:00", "authors": [], "tags": null}, {"id": "https://hfcqgis.opendatasicilia.it/blog/category/custom/", "url": "https://hfcqgis.opendatasicilia.it/blog/category/custom/", "title": "custom", "content_html": "<h1>custom</h1>", "image": null, "date_modified": "2025-12-30T11:22:39.948153+00:00", "date_published": "2025-12-30T11:22:39.948149+00:00", "authors": [], "tags": null}, {"id": "https://hfcqgis.opendatasicilia.it/blog/category/variabili/", "url": "https://hfcqgis.opendatasicilia.it/blog/category/variabili/", "title": "variabili", "content_html": "<h1>variabili</h1>", "image": null, "date_modified": "2025-12-30T11:22:39.944907+00:00", "date_published": "2025-12-30T11:22:39.944903+00:00", "authors": [], "tags": null}, {"id": "https://hfcqgis.opendatasicilia.it/blog/category/help/", "url": "https://hfcqgis.opendatasicilia.it/blog/category/help/", "title": "help", "content_html": "<h1>help</h1>", "image": null, "date_modified": "2025-12-30T11:22:39.941656+00:00", "date_published": "2025-12-30T11:22:39.941651+00:00", "authors": [], "tags": null}, {"id": "https://hfcqgis.opendatasicilia.it/blog/category/whitebox/", "url": "https://hfcqgis.opendatasicilia.it/blog/category/whitebox/", "title": "whitebox", "content_html": "<h1>whitebox</h1>", "image": null, "date_modified": "2025-12-30T11:22:39.938192+00:00", "date_published": "2025-12-30T11:22:39.938188+00:00", "authors": [], "tags": null}, {"id": "https://hfcqgis.opendatasicilia.it/blog/category/espressioni/", "url": "https://hfcqgis.opendatasicilia.it/blog/category/espressioni/", "title": "espressioni", "content_html": "<h1>espressioni</h1>", "image": null, "date_modified": "2025-12-30T11:22:39.934939+00:00", "date_published": "2025-12-30T11:22:39.934935+00:00", "authors": [], "tags": null}, {"id": "https://hfcqgis.opendatasicilia.it/blog/archive/2023/", "url": "https://hfcqgis.opendatasicilia.it/blog/archive/2023/", "title": "2023", "content_html": "<h1>2023</h1>", "image": null, "date_modified": "2025-12-30T11:22:39.931794+00:00", "date_published": "2025-12-30T11:22:39.931790+00:00", "authors": [], "tags": null}, {"id": "https://hfcqgis.opendatasicilia.it/blog/archive/2024/", "url": "https://hfcqgis.opendatasicilia.it/blog/archive/2024/", "title": "2024", "content_html": "<h1>2024</h1>", "image": null, "date_modified": "2025-12-30T11:22:39.928444+00:00", "date_published": "2025-12-30T11:22:39.928440+00:00", "authors": [], "tags": null}, {"id": "https://hfcqgis.opendatasicilia.it/corso_formazione/corso_di_formazione_avanzato/", "url": "https://hfcqgis.opendatasicilia.it/corso_formazione/corso_di_formazione_avanzato/", "title": "Corso di formazione avanzato - IN LAVORAZIONE", "content_html": "<h1>Corso di formazione avanzato - <code>IN LAVORAZIONE</code></h1>\n<h2>A chi \u00e8 rivolto</h2>\n<p>Il corso \u00e8 rivolto agli utenti che conoscono l'uso generale di [QGIS](https://qgis.org...</p>", "image": null, "date_modified": "2025-12-30T11:21:27+00:00", "date_published": "2021-10-18T11:00:43+00:00", "authors": [], "tags": null}, {"id": "https://hfcqgis.opendatasicilia.it/corso_formazione/corso_di_formazione/", "url": "https://hfcqgis.opendatasicilia.it/corso_formazione/corso_di_formazione/", "title": "Corso di formazione", "content_html": "<h1>Corso di formazione</h1>\n<h2>A chi \u00e8 rivolto</h2>\n<p>Il corso \u00e8 rivolto agli utenti che conoscono l'uso generale di <a href=\"https://qgis.org/it/site/\">QGIS</a> e desiderano appr...</p>", "image": null, "date_modified": "2025-12-30T11:10:16+00:00", "date_published": "2021-06-29T18:27:13+00:00", "authors": [], "tags": null}, {"id": "https://hfcqgis.opendatasicilia.it/gr_funzioni/variabili/variabili_unico/", "url": "https://hfcqgis.opendatasicilia.it/gr_funzioni/variabili/variabili_unico/", "title": "Variabili", "content_html": "<h1>Variabili</h1>\n<p>Questo gruppo contiene variabili dinamiche relative all'applicazione, al file di progetto e ad altre impostazioni. Le variabili possono essere u...</p>", "image": null, "date_modified": "2025-12-30T11:03:00+00:00", "date_published": "2025-12-30T11:03:00+00:00", "authors": [], "tags": null}, {"id": "https://hfcqgis.opendatasicilia.it/", "url": "https://hfcqgis.opendatasicilia.it/", "title": "Home", "content_html": "<style>\n.md-search-result .md-typeset h1 {display: block! important; padding-top: 0.65rem;}\n.md-typeset .md-content__button {display: none!important; }\n.md-f...", "image": null, "date_modified": "2025-12-05T07:51:37+00:00", "date_published": "2021-07-01T04:34:02+00:00", "authors": [], "tags": null}, {"id": "https://hfcqgis.opendatasicilia.it/changelog/", "url": "https://hfcqgis.opendatasicilia.it/changelog/", "title": "Changelog", "content_html": "<h1>Changelog</h1>\n<p>In questa sezione verranno inserite ogni modifica o aggiunta di esempi, funzioni e altro.</p>\n<h2>Registro aggiornato in ordine cronologico</h2>\n<p>data   ...</p>", "image": null, "date_modified": "2025-12-05T07:51:37+00:00", "date_published": "2021-07-25T16:57:35+00:00", "authors": [], "tags": null}, {"id": "https://hfcqgis.opendatasicilia.it/esempi/angolo_interno_minimo_poligono/", "url": "https://hfcqgis.opendatasicilia.it/esempi/angolo_interno_minimo_poligono/", "title": "Angolo interno minimo di un poligono", "content_html": "<h1>Angolo interno minimo di un poligono</h1>\n<p>Come trovare l'angolo interno pi\u00f9 piccolo (pi\u00f9 stretto) di un poligono utilizzando il calcolatore di campi.</p>\n<h2>Probl...</h2>", "image": null, "date_modified": "2025-12-05T07:51:37+00:00", "date_published": "2025-12-05T07:51:37+00:00", "authors": [], "tags": null}, {"id": "https://hfcqgis.opendatasicilia.it/esempi/lista_esempi/", "url": "https://hfcqgis.opendatasicilia.it/esempi/lista_esempi/", "title": "Lista esempi", "content_html": "<p>!!! Abstract\n    **Questa sezione raccoglie degli esempi pratici e svolti step by step, con molti screenshot per rendere facile la comprensione di alcune fun...</p>", "image": null, "date_modified": "2025-12-05T07:51:37+00:00", "date_published": "2021-06-29T19:02:54+00:00", "authors": [], "tags": null}]}